LICENSE
README.md
pyproject.toml
setup.cfg
setup.py
YAMLit.egg-info/PKG-INFO
YAMLit.egg-info/SOURCES.txt
YAMLit.egg-info/dependency_links.txt
YAMLit.egg-info/requires.txt
YAMLit.egg-info/top_level.txt
tests/__init__.py
tests/benchmark/__init__.py
tests/integration/__init__.py
tests/unit/__init__.py
yamlit/__init__.py
yamlit/config.py
yamlit/dumper.py
yamlit/loader.py
yamlit/register.py
yamlit/structures.py